Workbook

Sheet Solar
A1: 2 Months Bill | B1: 4000 | E1: 1 | F1: 35000
A2: 2 Months cons | B2: =Calculator!B10 -> 697 | E2: 2 | F2: 70000
A3: Fixed Bill | B3: 350 | E3: 3 | F3: 100000
A4: Is Home? | B4: TRUE | C4: =IF(B4,"Home","Commercial") -> Home | E4: 100 | F4: 100000 | I4: 250000
A5: With Subsidy? | B5: =B4 -> TRUE | I5: =I4/7650 -> 32.679739
A6: Monthly Cons | B6: =B2/2 -> 348.5 | E6: =C7/4 -> 0 | I6: =I5/6 -> 5.4466231
A7: Per Day | B7: =B6/30 -> 11.616667
A8: kW Required | B8: =ROUNDUP(B7/4,0) -> 3 | C8: =IF(B5,70000,60000) -> 70000
A9: Investment | B9: =B8*C8 -> 210000
A10: SubSidy | B10: =IF(B5,_xlfn.XLOOKUP(B8,E:E,F:F,"",1),0) -> 100000
A11: Expense | B11: =B9-B10 -> 110000
A12: Yearly Savings | B12: =((B1-B3)*6) -> 21900
A13: Months for ROI | B13: =ROUND(B11/B12*12,0) -> 60
A14: Years | B14: =ROUNDDOWN(B13/12,0)&" Years & "&(MOD(B13,12))&" Months" -> 5 Years & 0 Months

Sheet Calculator
A1: TAMIL NADU EB – FIND UNITS CONSUMED FROM YOUR 2-MONTH BILL
A2: Yellow cells = your inputs. Everything else is formula-driven from the 'Tariff Master' sheet.
A4: INPUTS | B4: Enter here | C4: Help
A5: Connection type | B5: =IF(Solar!B4,"Home","Commercial") -> Home | C5: Select Home or Commercial
A6: Last 2 months' EB bill amount (₹) | B6: =Solar!B1 -> 4000 | C6: Total bill for the 2-month cycle (example value – overwrite)
A7: Sanctioned load (kW) – Commercial only | B7: 1 | C7: Printed on the commercial bill; used to remove the fixed charge. Ignored for Home
A9: RESULT | B9: Value | C9: How it is worked out
A10: EB UNITS CONSUMED IN 2 MONTHS | B10: =ROUND(Workings!B11,0) -> 697 | C10: Bill worked backwards through the slabs, rounded to whole units
A11: Average units per month | B11: =B10/'Tariff Master'!$B$37 -> 348.5 | C11: Total ÷ billing months
A12: Tariff applied | B12: =IF(B5="Home","Domestic LT-IA – "&IF(B10<='Tariff Master'!$B$28,"Tier A (≤500 units, first 200 free)","Tier B (>500 units, first 100 free)"),"Commercial LT-V – "&IF(B10<='Tariff Master'!$B$29,"flat rate up to 100 units","flat rate on all units (above 100)")) -> Domestic LT-IA – Tier B (>500 units, first 100 free) | C12: Picked automatically from the derived units
A13: Free (subsidised) units | B13: =IF(B5="Home",SUMIF(E25:E31,0,D25:D31),0) -> 100 | C13: Domestic only – units in ₹0 slabs
A14: Chargeable (billable) units | B14: =B10-B13 -> 597 | C14: Total – free units
A15: Energy charge (₹) | B15: =IF(B5="Home",SUM(F25:F31),B10*IF(B10<='Tariff Master'!$B$29,'Tariff Master'!$B$30,'Tariff Master'!$B$31)) -> 3995.15 | C15: Home: slab-wise (telescopic). Commercial: single rate × all units
A16: Fixed charge (₹) | B16: =IF(B5="Commercial",N(B7)*IF(N(B7)<='Tariff Master'!$B$35,'Tariff Master'!$B$32,IF(N(B7)<='Tariff Master'!$B$36,'Tariff Master'!$B$33,'Tariff Master'!$B$34))*'Tariff Master'!$B$37,0) -> 0 | C16: Commercial: load kW × ₹/kW/month × 2 months
A17: Electricity duty (₹) | B17: =B15*IF(B5="Home",'Tariff Master'!$B$39,'Tariff Master'!$B$38) -> 0 | C17: Home 0%; Commercial 5% of energy charge
A18: Check: bill recomputed from these units (₹) | B18: =B15+B16+B17 -> 3995.15 | C18: Forward calculation – should match your bill
A19: Difference vs your entered bill (₹) | B19: =N(B6)-B18 -> 4.85 | C19: Small (<₹10) = rounding. Large = bill has other charges (FPPA, arrears, etc.)
A20: =IF(B6="","Enter your 2-month bill amount in B6.",IF(AND(B5="Commercial",N(B7)=0),"⚠ Enter the sanctioned load (kW) – without it the fixed charge is not deducted and units will be overstated.",IF(AND(B5="Commercial",N(B6)<B16),"⚠ Bill is lower than the fixed charge – check the load (kW) and bill amount.",IF(AND(B5="Home",N(B6)=0),"⚠ ₹0 bill: units are within the free quota. Exact units cannot be derived – the figure shown is the MAXIMUM (200).",IF(Workings!B12,"⚠ This amount falls in a gap between slabs (the bill probably includes FPPA/arrears/other charges). Units shown are the nearest slab boundary – treat as approximate.","✔ Bill matches the tariff – units derived successfully."))))) -> ✔ Bill matches the tariff – units derived successfully.
A23: DOMESTIC SLAB-WISE BREAKDOWN OF THE DERIVED UNITS (shown only when type = Home)
A24: Slab | B24: From (>) | C24: To (≤) | D24: Units in slab | E24: Rate (₹/unit) | F24: Amount (₹)
A25: =IF(C25=0,"",IF(C25>=999999999,"Above "&TEXT(B25,"#,##0"),TEXT(B25+1,"#,##0")&" – "&TEXT(C25,"#,##0"))) -> 1 – 100 | B25: =IF($B$10<='Tariff Master'!$B$28,'Tariff Master'!B6,'Tariff Master'!B17) -> 0 | C25: =IF($B$10<='Tariff Master'!$B$28,'Tariff Master'!C6,'Tariff Master'!C17) -> 100 | D25: =IF($B$5="Home",MAX(0,MIN($B$10,C25)-B25),0) -> 100 | E25: =IF($B$10<='Tariff Master'!$B$28,'Tariff Master'!D6,'Tariff Master'!D17) -> 0 | F25: =D25*E25 -> 0
A26: =IF(C26=0,"",IF(C26>=999999999,"Above "&TEXT(B26,"#,##0"),TEXT(B26+1,"#,##0")&" – "&TEXT(C26,"#,##0"))) -> 101 – 400 | B26: =IF($B$10<='Tariff Master'!$B$28,'Tariff Master'!B7,'Tariff Master'!B18) -> 100 | C26: =IF($B$10<='Tariff Master'!$B$28,'Tariff Master'!C7,'Tariff Master'!C18) -> 400 | D26: =IF($B$5="Home",MAX(0,MIN($B$10,C26)-B26),0) -> 300 | E26: =IF($B$10<='Tariff Master'!$B$28,'Tariff Master'!D7,'Tariff Master'!D18) -> 4.95 | F26: =D26*E26 -> 1485
A27: =IF(C27=0,"",IF(C27>=999999999,"Above "&TEXT(B27,"#,##0"),TEXT(B27+1,"#,##0")&" – "&TEXT(C27,"#,##0"))) -> 401 – 500 | B27: =IF($B$10<='Tariff Master'!$B$28,'Tariff Master'!B8,'Tariff Master'!B19) -> 400 | C27: =IF($B$10<='Tariff Master'!$B$28,'Tariff Master'!C8,'Tariff Master'!C19) -> 500 | D27: =IF($B$5="Home",MAX(0,MIN($B$10,C27)-B27),0) -> 100 | E27: =IF($B$10<='Tariff Master'!$B$28,'Tariff Master'!D8,'Tariff Master'!D19) -> 6.65 | F27: =D27*E27 -> 665
A28: =IF(C28=0,"",IF(C28>=999999999,"Above "&TEXT(B28,"#,##0"),TEXT(B28+1,"#,##0")&" – "&TEXT(C28,"#,##0"))) -> 501 – 600 | B28: =IF($B$10<='Tariff Master'!$B$28,'Tariff Master'!B9,'Tariff Master'!B20) -> 500 | C28: =IF($B$10<='Tariff Master'!$B$28,'Tariff Master'!C9,'Tariff Master'!C20) -> 600 | D28: =IF($B$5="Home",MAX(0,MIN($B$10,C28)-B28),0) -> 100 | E28: =IF($B$10<='Tariff Master'!$B$28,'Tariff Master'!D9,'Tariff Master'!D20) -> 8.8 | F28: =D28*E28 -> 880
A29: =IF(C29=0,"",IF(C29>=999999999,"Above "&TEXT(B29,"#,##0"),TEXT(B29+1,"#,##0")&" – "&TEXT(C29,"#,##0"))) -> 601 – 800 | B29: =IF($B$10<='Tariff Master'!$B$28,'Tariff Master'!B10,'Tariff Master'!B21) -> 600 | C29: =IF($B$10<='Tariff Master'!$B$28,'Tariff Master'!C10,'Tariff Master'!C21) -> 800 | D29: =IF($B$5="Home",MAX(0,MIN($B$10,C29)-B29),0) -> 97 | E29: =IF($B$10<='Tariff Master'!$B$28,'Tariff Master'!D10,'Tariff Master'!D21) -> 9.95 | F29: =D29*E29 -> 965.15
A30: =IF(C30=0,"",IF(C30>=999999999,"Above "&TEXT(B30,"#,##0"),TEXT(B30+1,"#,##0")&" – "&TEXT(C30,"#,##0"))) -> 801 – 1,000 | B30: =IF($B$10<='Tariff Master'!$B$28,'Tariff Master'!B11,'Tariff Master'!B22) -> 800 | C30: =IF($B$10<='Tariff Master'!$B$28,'Tariff Master'!C11,'Tariff Master'!C22) -> 1000 | D30: =IF($B$5="Home",MAX(0,MIN($B$10,C30)-B30),0) -> 0 | E30: =IF($B$10<='Tariff Master'!$B$28,'Tariff Master'!D11,'Tariff Master'!D22) -> 11.05 | F30: =D30*E30 -> 0
A31: =IF(C31=0,"",IF(C31>=999999999,"Above "&TEXT(B31,"#,##0"),TEXT(B31+1,"#,##0")&" – "&TEXT(C31,"#,##0"))) -> Above 1,000 | B31: =IF($B$10<='Tariff Master'!$B$28,'Tariff Master'!B12,'Tariff Master'!B23) -> 1000 | C31: =IF($B$10<='Tariff Master'!$B$28,'Tariff Master'!C12,'Tariff Master'!C23) -> 999999999 | D31: =IF($B$5="Home",MAX(0,MIN($B$10,C31)-B31),0) -> 0 | E31: =IF($B$10<='Tariff Master'!$B$28,'Tariff Master'!D12,'Tariff Master'!D23) -> 12.15 | F31: =D31*E31 -> 0
A32: Total | D32: =SUM(D25:D31) -> 697 | F32: =SUM(F25:F31) -> 3995.15
A34: How it works: the bill is worked backwards – duty and fixed charge are removed, then the remaining amount is pushed through the slabs (Workings sheet) to find the units. Home: exempt from duty; telescopic slabs; crossing 500 units drops free units from 200 to 100. Commercial: no free units; one flat rate on ALL units (₹6.65 up to 100, ₹10.45 above). The result is exact only if your bill contains just energy + fixed charge + duty; FPPA, meter rent, arrears etc. will inflate the units – see the Difference row. Rates: 'Tariff Master'.

Sheet Tariff Master
A1: TAMIL NADU EB TARIFF – MASTER (TNPDCL / TANGEDCO)
A2: Basis: TNERC Tariff Order No. 6 of 2025 (30-06-2025, effective 01-07-2025) – still in force; no revision for 2026-27 as per reports dated 25-Jun-2026. Free-unit scheme: GoTN G.O.(Ms) No.50 dated 10-05-2026. Verified online on 05-Oct-2026. Blue cells = editable master values; update them if TNERC issues a new order.
A4: DOMESTIC (Home) LT-IA – TIER A: bi-monthly consumption ≤ 500 units (first 200 units FREE)
A5: Slab No. | B5: From (units >) | C5: To (units ≤) | D5: Rate (₹/unit) | E5: Remark
A6: 1 | B6: 0 | C6: 200 | D6: 0 | E6: Free (Govt. subsidy, G.O. 50 of 2026)
A7: 2 | B7: 200 | C7: 400 | D7: 4.95
A8: 3 | B8: 400 | C8: 500 | D8: 6.65 | E8: Tier A ends at 500 units
A10: (slabs 4–7 not applicable in Tier A)
A15: DOMESTIC (Home) LT-IA – TIER B: bi-monthly consumption > 500 units (only first 100 units FREE)
A16: Slab No. | B16: From (units >) | C16: To (units ≤) | D16: Rate (₹/unit) | E16: Remark
A17: 1 | B17: 0 | C17: 100 | D17: 0 | E17: Free (reduced subsidy above 500 units)
A18: 2 | B18: 100 | C18: 400 | D18: 4.95
A19: 3 | B19: 400 | C19: 500 | D19: 6.65
A20: 4 | B20: 500 | C20: 600 | D20: 8.8
A21: 5 | B21: 600 | C21: 800 | D21: 9.95
A22: 6 | B22: 800 | C22: 1000 | D22: 11.05
A23: 7 | B23: 1000 | C23: 999999999 | D23: 12.15 | E23: No upper limit
A26: OTHER PARAMETERS
A27: Parameter | B27: Value | C27: Note
A28: Domestic tier cut-off (bi-monthly units) | B28: 500 | C28: ≤ this → Tier A (200 free); above → Tier B (100 free)
A29: Commercial LT-V threshold (bi-monthly units) | B29: 100 | C29: ≤100 units → lower rate; above → higher rate on ALL units (not telescopic)
A30: Commercial rate – up to threshold (₹/unit) | B30: 6.65 | C30: LT-V Misc./General purpose
A31: Commercial rate – above threshold (₹/unit) | B31: 10.45 | C31: Applied to every unit once usage crosses 100 (bi-monthly)
A32: Commercial fixed charge – load ≤ 50 kW (₹/kW/month) | B32: 110 | C32: Sanctioned load based
A33: Commercial fixed charge – load >50 to 112 kW (₹/kW/month) | B33: 332
A34: Commercial fixed charge – load >112 kW (₹/kW/month) | B34: 608
A35: Load limit 1 (kW) | B35: 50
A36: Load limit 2 (kW) | B36: 112
A37: Billing months per cycle | B37: 2 | C37: Domestic & this calculator use a 2-month (bi-monthly) cycle
A38: Electricity duty – Commercial | B38: 0.05 | C38: 5% on energy charges (per tariff sources)
A39: Electricity duty – Domestic | B39: 0 | C39: Domestic LT-IA is exempt
A41: Not included: Fuel/power purchase adjustment, meter rent, arrears, late fees, ToD charges, other surcharges. Bill amounts are therefore estimates; the EB bill itself is the final authority.
A42: Sources: TNERC T.O. No.6 of 2025 (tnerc.tn.gov.in); GoTN G.O.(Ms) No.50 (10-05-2026) free-units scheme; TNPDCL tariff summaries (thediscombill.com, electricbill.in, nobroker.in – cross-checked).

Sheet Workings
A1: WORKINGS – reverse calculation (bill amount → units). No inputs here.
A2: Connection type | B2: =Calculator!B5 -> Home
A3: Bill amount entered (₹) | B3: =N(Calculator!B6) -> 4000
A4: Fixed charge deducted (₹) | B4: =Calculator!B16 -> 0
A5: Net energy charge incl. duty removed (₹) | B5: =MAX(0,B3-B4)/(1+IF(B2="Home",'Tariff Master'!$B$39,'Tariff Master'!$B$38)) -> 4000
A6: Home Tier A – max energy charge at 500 units (₹) | B6: =F22+E22*D22 -> 1655
A7: Home Tier A – units from bill | B7: =SUM(G16:G22) -> 500
A8: Home Tier B – units from bill | B8: =SUM(G26:G32) -> 697.48744
A9: Home – derived units | B9: =IF(B5<=B6,B7,MAX(B8,'Tariff Master'!$B$28)) -> 697.48744
A10: Commercial – derived units | B10: =IF(B5<='Tariff Master'!$B$29*'Tariff Master'!$B$30,B5/'Tariff Master'!$B$30,MAX('Tariff Master'!$B$29,B5/'Tariff Master'!$B$31)) -> 382.77512
A11: Derived units (unrounded) | B11: =IF(B2="Home",B9,B10) -> 697.48744
A12: Bill falls in a slab gap? (TRUE/FALSE) | B12: =IF(B2="Home",AND(B5>B6,B8<='Tariff Master'!$B$28),AND(B5>'Tariff Master'!$B$29*'Tariff Master'!$B$30,B5/'Tariff Master'!$B$31<='Tariff Master'!$B$29)) -> FALSE
A14: Home Tier A (≤500 units)
A15: Slab | B15: From (>) | C15: To (≤) | D15: Rate (₹/unit) | E15: Width (units) | F15: Bill at slab start (₹) | G15: Units from bill
A16: 1 | B16: ='Tariff Master'!B6 -> 0 | C16: ='Tariff Master'!C6 -> 200 | D16: ='Tariff Master'!D6 -> 0 | E16: =C16-B16 -> 200 | F16: 0 | G16: =IF(E16=0,0,IF(D16=0,E16,MIN(E16,MAX(0,$B$5-F16)/D16))) -> 200
A17: 2 | B17: ='Tariff Master'!B7 -> 200 | C17: ='Tariff Master'!C7 -> 400 | D17: ='Tariff Master'!D7 -> 4.95 | E17: =C17-B17 -> 200 | F17: =F16+E16*D16 -> 0 | G17: =IF(E17=0,0,IF(D17=0,E17,MIN(E17,MAX(0,$B$5-F17)/D17))) -> 200
A18: 3 | B18: ='Tariff Master'!B8 -> 400 | C18: ='Tariff Master'!C8 -> 500 | D18: ='Tariff Master'!D8 -> 6.65 | E18: =C18-B18 -> 100 | F18: =F17+E17*D17 -> 990 | G18: =IF(E18=0,0,IF(D18=0,E18,MIN(E18,MAX(0,$B$5-F18)/D18))) -> 100
A19: 4 | B19: ='Tariff Master'!B9 -> 0 | C19: ='Tariff Master'!C9 -> 0 | D19: ='Tariff Master'!D9 -> 0 | E19: =C19-B19 -> 0 | F19: =F18+E18*D18 -> 1655 | G19: =IF(E19=0,0,IF(D19=0,E19,MIN(E19,MAX(0,$B$5-F19)/D19))) -> 0
A20: 5 | B20: ='Tariff Master'!B10 -> 0 | C20: ='Tariff Master'!C10 -> 0 | D20: ='Tariff Master'!D10 -> 0 | E20: =C20-B20 -> 0 | F20: =F19+E19*D19 -> 1655 | G20: =IF(E20=0,0,IF(D20=0,E20,MIN(E20,MAX(0,$B$5-F20)/D20))) -> 0
A21: 6 | B21: ='Tariff Master'!B11 -> 0 | C21: ='Tariff Master'!C11 -> 0 | D21: ='Tariff Master'!D11 -> 0 | E21: =C21-B21 -> 0 | F21: =F20+E20*D20 -> 1655 | G21: =IF(E21=0,0,IF(D21=0,E21,MIN(E21,MAX(0,$B$5-F21)/D21))) -> 0
A22: 7 | B22: ='Tariff Master'!B12 -> 0 | C22: ='Tariff Master'!C12 -> 0 | D22: ='Tariff Master'!D12 -> 0 | E22: =C22-B22 -> 0 | F22: =F21+E21*D21 -> 1655 | G22: =IF(E22=0,0,IF(D22=0,E22,MIN(E22,MAX(0,$B$5-F22)/D22))) -> 0
A24: Home Tier B (>500 units)
A25: Slab | B25: From (>) | C25: To (≤) | D25: Rate (₹/unit) | E25: Width (units) | F25: Bill at slab start (₹) | G25: Units from bill
A26: 1 | B26: ='Tariff Master'!B17 -> 0 | C26: ='Tariff Master'!C17 -> 100 | D26: ='Tariff Master'!D17 -> 0 | E26: =C26-B26 -> 100 | F26: 0 | G26: =IF(E26=0,0,IF(D26=0,E26,MIN(E26,MAX(0,$B$5-F26)/D26))) -> 100
A27: 2 | B27: ='Tariff Master'!B18 -> 100 | C27: ='Tariff Master'!C18 -> 400 | D27: ='Tariff Master'!D18 -> 4.95 | E27: =C27-B27 -> 300 | F27: =F26+E26*D26 -> 0 | G27: =IF(E27=0,0,IF(D27=0,E27,MIN(E27,MAX(0,$B$5-F27)/D27))) -> 300
A28: 3 | B28: ='Tariff Master'!B19 -> 400 | C28: ='Tariff Master'!C19 -> 500 | D28: ='Tariff Master'!D19 -> 6.65 | E28: =C28-B28 -> 100 | F28: =F27+E27*D27 -> 1485 | G28: =IF(E28=0,0,IF(D28=0,E28,MIN(E28,MAX(0,$B$5-F28)/D28))) -> 100
A29: 4 | B29: ='Tariff Master'!B20 -> 500 | C29: ='Tariff Master'!C20 -> 600 | D29: ='Tariff Master'!D20 -> 8.8 | E29: =C29-B29 -> 100 | F29: =F28+E28*D28 -> 2150 | G29: =IF(E29=0,0,IF(D29=0,E29,MIN(E29,MAX(0,$B$5-F29)/D29))) -> 100
A30: 5 | B30: ='Tariff Master'!B21 -> 600 | C30: ='Tariff Master'!C21 -> 800 | D30: ='Tariff Master'!D21 -> 9.95 | E30: =C30-B30 -> 200 | F30: =F29+E29*D29 -> 3030 | G30: =IF(E30=0,0,IF(D30=0,E30,MIN(E30,MAX(0,$B$5-F30)/D30))) -> 97.487437
A31: 6 | B31: ='Tariff Master'!B22 -> 800 | C31: ='Tariff Master'!C22 -> 1000 | D31: ='Tariff Master'!D22 -> 11.05 | E31: =C31-B31 -> 200 | F31: =F30+E30*D30 -> 5020 | G31: =IF(E31=0,0,IF(D31=0,E31,MIN(E31,MAX(0,$B$5-F31)/D31))) -> 0
A32: 7 | B32: ='Tariff Master'!B23 -> 1000 | C32: ='Tariff Master'!C23 -> 999999999 | D32: ='Tariff Master'!D23 -> 12.15 | E32: =C32-B32 -> 999998999 | F32: =F31+E31*D31 -> 7230 | G32: =IF(E32=0,0,IF(D32=0,E32,MIN(E32,MAX(0,$B$5-F32)/D32))) -> 0
